fast_tokenizer/__init__.py
fast_tokenizer/c_wrap.py
fast_tokenizer/commit.log
fast_tokenizer/core_tokenizers.lib
fast_tokenizer/core_tokenizers.pyd
fast_tokenizer/decoders/__init__.py
fast_tokenizer/libs/__init__.py
fast_tokenizer/libs/icudt70.dll
fast_tokenizer/libs/icuuc70.dll
fast_tokenizer/models/__init__.py
fast_tokenizer/normalizers/__init__.py
fast_tokenizer/postprocessors/__init__.py
fast_tokenizer/pretokenizers/__init__.py
fast_tokenizer/tokenizers_impl/__init__.py
fast_tokenizer/tokenizers_impl/base_tokenizer.py
fast_tokenizer/tokenizers_impl/clip.py
fast_tokenizer/tokenizers_impl/ernie.py
fast_tokenizer/tokenizers_impl/sentencepiece_bpe.py
fast_tokenizer_python-1.0.2.post1.dist-info/METADATA
fast_tokenizer_python-1.0.2.post1.dist-info/WHEEL
fast_tokenizer_python-1.0.2.post1.dist-info/top_level.txt
fast_tokenizer_python-1.0.2.post1.dist-info/RECORD
